skinAPI.py
skin_APIv_cpu-1.0.dist-info/METADATA
skin_APIv_cpu-1.0.dist-info/WHEEL
skin_APIv_cpu-1.0.dist-info/top_level.txt
skin_APIv_cpu-1.0.dist-info/RECORD
