Metadata-Version: 2.1
Name: skin-APIv-cpu
Version: 1.0
Summary: The API for melanoma image skin level prediction (cpu Version).
Home-page: UNKNOWN
Author: Claire
Author-email: UNKNOWN
License: LGPL
Platform: UNKNOWN
